common/__init__.py
common/logger.py
communication/__init__.py
communication/mail.py
error/__init__.py
error/exceptions.py
utilities/__init__.py
utilities/common/__init__.py
utilities/common/logger.py
utilities/communication/__init__.py
utilities/communication/mail.py
utilities/error/__init__.py
utilities/error/exceptions.py
general_utilities-0.1.1.dist-info/LICENCE
general_utilities-0.1.1.dist-info/METADATA
general_utilities-0.1.1.dist-info/WHEEL
general_utilities-0.1.1.dist-info/top_level.txt
general_utilities-0.1.1.dist-info/RECORD
