Metadata-Version: 2.1
Name: general-utilities
Version: 0.1.1
Summary: A general utilities for day-to-day python programs
Home-page: https://github.com/jalpeshborad/utilities
Author: Jalpesh Borad
Author-email: jalpeshborad@gmail.com
License: UNKNOWN
Platform: UNKNOWN
